yarp_middleware.libs/libACE-6-723764a8.3.3.so
yarp_middleware.libs/libz-7fd423a0.so.1.2.8
yarp_middleware.libs/libsqlite3-452d649c.so.0.8.6
yarp_middleware-3.5.0.dist-info/METADATA
yarp_middleware-3.5.0.dist-info/top_level.txt
yarp_middleware-3.5.0.dist-info/RECORD
yarp_middleware-3.5.0.dist-info/WHEEL
yarp_middleware-3.5.0.dist-info/entry_points.txt
yarp/__init__.py
yarp/bindings/yarp.py
yarp/bindings/_yarp.so
yarp/lib/libyarp_multipleanalogsensorsclient.a
yarp/lib/libyarp_frameGrabberCropper.a
yarp/lib/libyarp_remote_controlboard.a
yarp/lib/libyarp_inertial.a
yarp/lib/libyarp_pipe.a
yarp/lib/libyarp_fakeFrameGrabber.a
yarp/lib/libyarp_RGBDSensorWrapper.a
yarp/lib/libyarp_frameGrabber_nws_yarp.a
yarp/lib/libyarp_RGBDSensorClient.a
yarp/lib/libyarp_frameGrabber_nwc_yarp.a
yarp/lib/libyarp_rangefinder2D_nws_ros.a
yarp/lib/libyarp_portmonitor.a
yarp/lib/libyarp_robotDescriptionServer.a
yarp/lib/libyarp_AudioPlayerWrapper.a
yarp/lib/libYARP_wire_rep_utils.a
yarp/lib/libYARP_serversql.a
yarp/lib/libyarp_serial.a
yarp/lib/libyarpmod.a
yarp/lib/libYARP_logger.a
yarp/lib/libyarp_tcpros.a
yarp/lib/libYARP_priv_hmac.a
yarp/lib/libyarp_shmem.a
yarp/lib/libYARP_sig.a
yarp/lib/libYARP_manager.a
yarp/lib/libYARP_companion.a
yarp/lib/libyarp_batteryWrapper.a
yarp/lib/libyarp_unix.a
yarp/lib/libyarp_Rangefinder2DWrapper.a
yarp/lib/libyarp_analogsensorclient.a
yarp/lib/libYARP_priv_xmlrpcpp.a
yarp/lib/libyarp_group.a
yarp/lib/libyarp_JoypadControlClient.a
yarp/lib/libyarp_remote_grabber.a
yarp/lib/libyarp_controlboardwrapper2.a
yarp/lib/libyarp_controlboardremapper.a
yarp/lib/libyarppm.a
yarp/lib/libyarp_virtualAnalogServer.a
yarp/lib/libyarp_multipleanalogsensorsserver.a
yarp/lib/libYARP_robotinterface.a
yarp/lib/libyarp_batteryClient.a
yarp/lib/libYARP_init.a
yarp/lib/libyarp_rangefinder2D_nws_yarp.a
yarp/lib/libyarpcar.a
yarp/lib/libyarp_AudioRecorderWrapper.a
yarp/lib/libYARP_gsl.a
yarp/lib/libyarp_multipleanalogsensorsremapper.a
yarp/lib/libyarp_bayer.a
yarp/lib/libYARP_dev.a
yarp/lib/libyarp_grabberDual.a
yarp/lib/libYARP_run.a
yarp/lib/libyarp_rgbdSensor_nws_ros.a
yarp/lib/libYARP_priv_tinyxml.a
