Metadata-Version: 2.1
Name: yarp-middleware
Version: 3.5.0
Summary: YARP - Yet Another Robot Platform.
Home-page: https://www.yarp.it/latest/
Author: Diego Ferigo
Author-email: dgferigo@gmail.com
License: BSD
Project-URL: Changelog, https://github.com/robotology/yarp/releases
Project-URL: Tracker, https://github.com/robotology/yarp/issues
Project-URL: Documentation, https://www.yarp.it/latest/
Project-URL: Source, https://github.com/robotology/yarp
Keywords: yarp,middleware,robot,robotics,research,robotics-libraries,humanoids,artificial-intelligence,network,communication,devices,ipc,interprocess-communication,human-robot-interaction
Platform: any
Classifier: Development Status :: 5 - Production/Stable
Classifier: Operating System :: POSIX :: Linux
Classifier: Operating System :: MacOS
Classifier: Operating System :: Microsoft :: Windows
Classifier: Operating System :: OS Independent
Classifier: Framework :: Robot Framework
Classifier: Intended Audience :: Science/Research
Classifier: Intended Audience :: Developers
Classifier: Intended Audience :: Education
Classifier: Programming Language :: C++
Classifier: Programming Language :: Python :: 3
Classifier: Programming Language :: Python :: 3 :: Only
Classifier: Programming Language :: Python :: Implementation :: CPython
Classifier: License :: OSI Approved :: BSD License
Classifier: License :: OSI Approved :: Apache Software License
Classifier: License :: OSI Approved :: GNU Lesser General Public License v2 or later (LGPLv2+)
Requires-Python: >=3.6
